dronecot/__init__.py
dronecot/classes.py
dronecot/commands.py
dronecot/constants.py
dronecot/functions.py
dronecot/open_drone_id.py
dronecot-1.1.1.dist-info/licenses/LICENSE
dronecot-1.1.1.dist-info/METADATA
dronecot-1.1.1.dist-info/WHEEL
dronecot-1.1.1.dist-info/entry_points.txt
dronecot-1.1.1.dist-info/top_level.txt
dronecot-1.1.1.dist-info/RECORD
